[
  {
    "id": 1,
    "userId": 1,
    "vendedor": "Diego",
    "productId": 9,
    "productName": "Vibradores",
    "quantity": 8,
    "unitPrice": 100000,
    "price": 800000,
    "paymentMethod": "Efectivo",
    "proofPath": null,
    "orderId": 1,
    "saleDate": "2026-07-19T00:00:00.000Z",
    "createdAt": "2026-07-19T21:10:18.716Z"
  },
  {
    "id": 2,
    "userId": 5,
    "vendedor": "Gomez",
    "productId": 4,
    "productName": "Solaris Mango",
    "quantity": 1,
    "unitPrice": 32000,
    "price": 32000,
    "paymentMethod": "Efectivo",
    "proofPath": null,
    "orderId": 2,
    "saleDate": "2026-07-20T00:00:00.000Z",
    "createdAt": "2026-07-20T02:04:46.097Z"
  },
  {
    "id": 3,
    "userId": 5,
    "vendedor": "Gomez",
    "productId": 1,
    "productName": "Priv Bar Triple Mango",
    "quantity": 6,
    "unitPrice": 25000,
    "price": 150000,
    "paymentMethod": "Efectivo",
    "proofPath": null,
    "orderId": 3,
    "saleDate": "2026-07-20T00:00:00.000Z",
    "createdAt": "2026-07-20T02:04:49.035Z"
  },
  {
    "id": 4,
    "userId": 5,
    "vendedor": "Gomez",
    "productId": 9,
    "productName": "Vibradores",
    "quantity": 7,
    "unitPrice": 100000,
    "price": 700000,
    "paymentMethod": "Efectivo",
    "proofPath": null,
    "orderId": 4,
    "saleDate": "2026-07-20T00:00:00.000Z",
    "createdAt": "2026-07-20T02:04:52.794Z"
  },
  {
    "id": 5,
    "userId": 5,
    "vendedor": "Gomez",
    "productId": 8,
    "productName": "Just Watermelon ICE",
    "quantity": 1,
    "unitPrice": 22000,
    "price": 22000,
    "paymentMethod": "Efectivo",
    "proofPath": null,
    "orderId": 5,
    "saleDate": "2026-07-20T00:00:00.000Z",
    "createdAt": "2026-07-20T02:04:54.808Z"
  },
  {
    "id": 6,
    "userId": 5,
    "vendedor": "Gomez",
    "productId": 6,
    "productName": "Solaris Kiwi",
    "quantity": 1,
    "unitPrice": 32000,
    "price": 32000,
    "paymentMethod": "Efectivo",
    "proofPath": null,
    "orderId": 6,
    "saleDate": "2026-07-20T00:00:00.000Z",
    "createdAt": "2026-07-20T02:04:56.827Z"
  },
  {
    "id": 7,
    "userId": 1,
    "vendedor": "Diego",
    "productId": 2,
    "productName": "Priv Bar Triple Apple",
    "quantity": 1,
    "unitPrice": 25000,
    "price": 25000,
    "paymentMethod": "Electrónico",
    "proofPath": "/uploads/1784514021761-mamamarin.png",
    "orderId": 7,
    "saleDate": "2026-07-20T00:00:00.000Z",
    "createdAt": "2026-07-20T02:21:46.948Z"
  },
  {
    "id": 8,
    "userId": 5,
    "vendedor": "Gomez",
    "productId": 2,
    "productName": "Priv Bar Triple Apple",
    "quantity": 49,
    "unitPrice": 25000,
    "price": 1225000,
    "paymentMethod": "Efectivo",
    "proofPath": null,
    "orderId": 8,
    "saleDate": "2026-07-20T00:00:00.000Z",
    "createdAt": "2026-07-20T02:57:15.646Z"
  },
  {
    "id": 9,
    "userId": 5,
    "vendedor": "Gomez",
    "productId": 4,
    "productName": "Solaris Mango",
    "quantity": 4,
    "unitPrice": 32000,
    "price": 128000,
    "paymentMethod": "Efectivo",
    "proofPath": null,
    "orderId": 9,
    "saleDate": "2026-07-20T00:00:00.000Z",
    "createdAt": "2026-07-20T02:57:21.150Z"
  },
  {
    "id": 10,
    "userId": 5,
    "vendedor": "Gomez",
    "productId": 7,
    "productName": "Just Watermelon",
    "quantity": 4,
    "unitPrice": 25000,
    "price": 100000,
    "paymentMethod": "Efectivo",
    "proofPath": null,
    "orderId": 10,
    "saleDate": "2026-07-20T00:00:00.000Z",
    "createdAt": "2026-07-20T02:57:25.185Z"
  },
  {
    "id": 11,
    "userId": 5,
    "vendedor": "Gomez",
    "productId": 8,
    "productName": "Just Watermelon ICE",
    "quantity": 6,
    "unitPrice": 22000,
    "price": 132000,
    "paymentMethod": "Efectivo",
    "proofPath": null,
    "orderId": 11,
    "saleDate": "2026-07-20T00:00:00.000Z",
    "createdAt": "2026-07-20T02:57:31.524Z"
  }
]